{
	"Rooms": [
		{
			"Id": "IXURZGSCMSOGPDSAIEETGOUBWIGLTKAQQCMNZO",
			"RoomName": "stasis_chambers",
			"MapName": "stasis_chambers.json",
			"Position": {
				"X": -368,
				"Y": 272
			}
		},
		{
			"Id": "KDBOBWHCQLEPGTVURTMCVHJCGBYMTOVZFYLJDM",
			"RoomName": "baton",
			"MapName": "baton.json",
			"Position": {
				"X": 0,
				"Y": 0
			}
		},
		{
			"Id": "NYSHZZGYOPNSMBEYKUVXTPVLXTRRSEPZOQLUFQ",
			"RoomName": "side_room",
			"MapName": "side_room.json",
			"Position": {
				"X": 512,
				"Y": 384
			}
		},
		{
			"Id": "QRNMOEPODURAXTSXJGOGVFWQXQFEMVDYQCNJRZ",
			"RoomName": "boss",
			"MapName": "boss.json",
			"Position": {
				"X": -16,
				"Y": -656
			}
		},
		{
			"Id": "YRQLBDCMQTTSXFOQKLHVHHNHTZTQTDTBXRQVKO",
			"RoomName": "left_dead_end",
			"MapName": "left_dead_end.json",
			"Position": {
				"X": -496,
				"Y": -656
			}
		},
		{
			"Id": "UECRCTJGZRSISEPZPQDIRBKLTNZSVFPSFVQCTQ",
			"RoomName": "right_dead_end",
			"MapName": "right_dead_end.json",
			"Position": {
				"X": 464,
				"Y": -656
			}
		}
	],
	"Backgrounds": [

	],
	"StartRoomId": "IXURZGSCMSOGPDSAIEETGOUBWIGLTKAQQCMNZO"
}