{"frames": [

{
	"filename": "dead0.png",
	"frame": {"x":1,"y":1,"w":96,"h":96},
	"rotated": false,
	"trimmed": false,
	"spriteSourceSize": {"x":0,"y":0,"w":96,"h":96},
	"sourceSize": {"w":96,"h":96},
	"pivot": {"x":0.5,"y":0.5}
},
{
	"filename": "fire0.png",
	"frame": {"x":99,"y":1,"w":96,"h":96},
	"rotated": false,
	"trimmed": false,
	"spriteSourceSize": {"x":0,"y":0,"w":96,"h":96},
	"sourceSize": {"w":96,"h":96},
	"pivot": {"x":0.5,"y":0.5}
},
{
	"filename": "fire1.png",
	"frame": {"x":197,"y":1,"w":96,"h":96},
	"rotated": false,
	"trimmed": false,
	"spriteSourceSize": {"x":0,"y":0,"w":96,"h":96},
	"sourceSize": {"w":96,"h":96},
	"pivot": {"x":0.5,"y":0.5}
},
{
	"filename": "fire2.png",
	"frame": {"x":295,"y":1,"w":96,"h":96},
	"rotated": false,
	"trimmed": false,
	"spriteSourceSize": {"x":0,"y":0,"w":96,"h":96},
	"sourceSize": {"w":96,"h":96},
	"pivot": {"x":0.5,"y":0.5}
},
{
	"filename": "fire3.png",
	"frame": {"x":393,"y":1,"w":96,"h":96},
	"rotated": false,
	"trimmed": false,
	"spriteSourceSize": {"x":0,"y":0,"w":96,"h":96},
	"sourceSize": {"w":96,"h":96},
	"pivot": {"x":0.5,"y":0.5}
},
{
	"filename": "fly0.png",
	"frame": {"x":491,"y":1,"w":96,"h":96},
	"rotated": false,
	"trimmed": false,
	"spriteSourceSize": {"x":0,"y":0,"w":96,"h":96},
	"sourceSize": {"w":96,"h":96},
	"pivot": {"x":0.5,"y":0.5}
},
{
	"filename": "fly1.png",
	"frame": {"x":589,"y":1,"w":96,"h":96},
	"rotated": false,
	"trimmed": false,
	"spriteSourceSize": {"x":0,"y":0,"w":96,"h":96},
	"sourceSize": {"w":96,"h":96},
	"pivot": {"x":0.5,"y":0.5}
},
{
	"filename": "idle0.png",
	"frame": {"x":687,"y":1,"w":96,"h":96},
	"rotated": false,
	"trimmed": false,
	"spriteSourceSize": {"x":0,"y":0,"w":96,"h":96},
	"sourceSize": {"w":96,"h":96},
	"pivot": {"x":0.5,"y":0.5}
},
{
	"filename": "to_fly0.png",
	"frame": {"x":687,"y":1,"w":96,"h":96},
	"rotated": false,
	"trimmed": false,
	"spriteSourceSize": {"x":0,"y":0,"w":96,"h":96},
	"sourceSize": {"w":96,"h":96},
	"pivot": {"x":0.5,"y":0.5}
},
{
	"filename": "to_fly1.png",
	"frame": {"x":99,"y":1,"w":96,"h":96},
	"rotated": false,
	"trimmed": false,
	"spriteSourceSize": {"x":0,"y":0,"w":96,"h":96},
	"sourceSize": {"w":96,"h":96},
	"pivot": {"x":0.5,"y":0.5}
},
{
	"filename": "to_fly2.png",
	"frame": {"x":197,"y":1,"w":96,"h":96},
	"rotated": false,
	"trimmed": false,
	"spriteSourceSize": {"x":0,"y":0,"w":96,"h":96},
	"sourceSize": {"w":96,"h":96},
	"pivot": {"x":0.5,"y":0.5}
},
{
	"filename": "to_fly3.png",
	"frame": {"x":295,"y":1,"w":96,"h":96},
	"rotated": false,
	"trimmed": false,
	"spriteSourceSize": {"x":0,"y":0,"w":96,"h":96},
	"sourceSize": {"w":96,"h":96},
	"pivot": {"x":0.5,"y":0.5}
},
{
	"filename": "to_fly4.png",
	"frame": {"x":785,"y":1,"w":96,"h":96},
	"rotated": false,
	"trimmed": false,
	"spriteSourceSize": {"x":0,"y":0,"w":96,"h":96},
	"sourceSize": {"w":96,"h":96},
	"pivot": {"x":0.5,"y":0.5}
},
{
	"filename": "walk0.png",
	"frame": {"x":883,"y":1,"w":96,"h":96},
	"rotated": false,
	"trimmed": false,
	"spriteSourceSize": {"x":0,"y":0,"w":96,"h":96},
	"sourceSize": {"w":96,"h":96},
	"pivot": {"x":0.5,"y":0.5}
},
{
	"filename": "walk1.png",
	"frame": {"x":981,"y":1,"w":96,"h":96},
	"rotated": false,
	"trimmed": false,
	"spriteSourceSize": {"x":0,"y":0,"w":96,"h":96},
	"sourceSize": {"w":96,"h":96},
	"pivot": {"x":0.5,"y":0.5}
},
{
	"filename": "walk2.png",
	"frame": {"x":1079,"y":1,"w":96,"h":96},
	"rotated": false,
	"trimmed": false,
	"spriteSourceSize": {"x":0,"y":0,"w":96,"h":96},
	"sourceSize": {"w":96,"h":96},
	"pivot": {"x":0.5,"y":0.5}
},
{
	"filename": "walk3.png",
	"frame": {"x":1177,"y":1,"w":96,"h":96},
	"rotated": false,
	"trimmed": false,
	"spriteSourceSize": {"x":0,"y":0,"w":96,"h":96},
	"sourceSize": {"w":96,"h":96},
	"pivot": {"x":0.5,"y":0.5}
},
{
	"filename": "walk4.png",
	"frame": {"x":1275,"y":1,"w":96,"h":96},
	"rotated": false,
	"trimmed": false,
	"spriteSourceSize": {"x":0,"y":0,"w":96,"h":96},
	"sourceSize": {"w":96,"h":96},
	"pivot": {"x":0.5,"y":0.5}
},
{
	"filename": "walk5.png",
	"frame": {"x":1373,"y":1,"w":96,"h":96},
	"rotated": false,
	"trimmed": false,
	"spriteSourceSize": {"x":0,"y":0,"w":96,"h":96},
	"sourceSize": {"w":96,"h":96},
	"pivot": {"x":0.5,"y":0.5}
},
{
	"filename": "walk6.png",
	"frame": {"x":1471,"y":1,"w":96,"h":96},
	"rotated": false,
	"trimmed": false,
	"spriteSourceSize": {"x":0,"y":0,"w":96,"h":96},
	"sourceSize": {"w":96,"h":96},
	"pivot": {"x":0.5,"y":0.5}
},
{
	"filename": "walk7.png",
	"frame": {"x":1569,"y":1,"w":96,"h":96},
	"rotated": false,
	"trimmed": false,
	"spriteSourceSize": {"x":0,"y":0,"w":96,"h":96},
	"sourceSize": {"w":96,"h":96},
	"pivot": {"x":0.5,"y":0.5}
}],
"meta": {
	"app": "http://www.codeandweb.com/texturepacker",
	"version": "1.0",
	"image": "boss.png",
	"format": "RGBA8888",
	"size": {"w":1666,"h":98},
	"scale": "1",
	"smartupdate": "$TexturePacker:SmartUpdate:e9ac56ecae95463b12585f2ad578aab5:565bebcd6e9bd4f07a9a408c0e34b12b:46ed12eff2905e238af2d2a3f055c310$"
}
}
